Workbook

Sheet Dashboard
A1: AICERA SALES OPS DASHBOARD — FY 2026-27
A2: Live view: Targets vs Achievement, To-Go, Price Desk status & Incentive. All numbers flow from Targets, Orders & Price Desk sheets.
A4: TOP LINE TARGET | D4: REVENUE BOOKED | G4: REVENUE TO GO | J4: REVENUE ACH %
A5: =Incentive!B8 -> 100000000 | D5: =Incentive!C8 -> 147700000 | G5: =Incentive!D8 -> 23500000 | J5: =Incentive!E8 -> 1.477
A8: BOTTOM LINE TARGET (8%) | D8: MARGIN EARNED (QUOTA) | G8: MARGIN TO GO | J8: INCENTIVE PAYABLE
A9: =Incentive!F8 -> 8000000 | D9: =Incentive!G8 -> 10224000 | G9: =Incentive!H8 -> 1665000 | J9: =Incentive!J8 -> 511200
A40: CHART DATA (auto — do not edit)
A41: Sales Person | B41: Revenue Target | C41: Revenue Booked | D41: Margin Target | E41: Margin Earned | F41: Incentive
A42: =Incentive!A5 -> Bhuvara PR | B42: =Incentive!B5 -> 30000000 | C42: =Incentive!C5 -> 61800000 | D42: =Incentive!F5 -> 2400000 | E42: =Incentive!G5 -> 4974000 | F42: =Incentive!J5 -> 248700
A43: =Incentive!A6 -> Rahul Raju | B43: =Incentive!B6 -> 25000000 | C43: =Incentive!C6 -> 64400000 | D43: =Incentive!F6 -> 2000000 | E43: =Incentive!G6 -> 3315000 | F43: =Incentive!J6 -> 165750
A44: =Incentive!A7 -> Laxman Kamath | B44: =Incentive!B7 -> 45000000 | C44: =Incentive!C7 -> 21500000 | D44: =Incentive!F7 -> 3600000 | E44: =Incentive!G7 -> 1935000 | F44: =Incentive!J7 -> 96750
A47: Month | B47: Revenue Booked | C47: Margin Earned
A48: Apr-26 | B48: =SUMIFS(Orders!G$5:G$24,Orders!C$5:C$24,A48) -> 96000000 | C48: =SUMIFS(Orders!I$5:I$24,Orders!C$5:C$24,A48) -> 6100000
A49: May-26 | B49: =SUMIFS(Orders!G$5:G$24,Orders!C$5:C$24,A49) -> 18300000 | C49: =SUMIFS(Orders!I$5:I$24,Orders!C$5:C$24,A49) -> 1450000
A50: Jun-26 | B50: =SUMIFS(Orders!G$5:G$24,Orders!C$5:C$24,A50) -> 27700000 | C50: =SUMIFS(Orders!I$5:I$24,Orders!C$5:C$24,A50) -> 2245000
A51: Jul-26 | B51: =SUMIFS(Orders!G$5:G$24,Orders!C$5:C$24,A51) -> 5700000 | C51: =SUMIFS(Orders!I$5:I$24,Orders!C$5:C$24,A51) -> 429000
A52: Aug-26 | B52: =SUMIFS(Orders!G$5:G$24,Orders!C$5:C$24,A52) -> 0 | C52: =SUMIFS(Orders!I$5:I$24,Orders!C$5:C$24,A52) -> 0
A53: Sep-26 | B53: =SUMIFS(Orders!G$5:G$24,Orders!C$5:C$24,A53) -> 0 | C53: =SUMIFS(Orders!I$5:I$24,Orders!C$5:C$24,A53) -> 0
A54: Oct-26 | B54: =SUMIFS(Orders!G$5:G$24,Orders!C$5:C$24,A54) -> 0 | C54: =SUMIFS(Orders!I$5:I$24,Orders!C$5:C$24,A54) -> 0
A55: Nov-26 | B55: =SUMIFS(Orders!G$5:G$24,Orders!C$5:C$24,A55) -> 0 | C55: =SUMIFS(Orders!I$5:I$24,Orders!C$5:C$24,A55) -> 0
A56: Dec-26 | B56: =SUMIFS(Orders!G$5:G$24,Orders!C$5:C$24,A56) -> 0 | C56: =SUMIFS(Orders!I$5:I$24,Orders!C$5:C$24,A56) -> 0
A57: Jan-27 | B57: =SUMIFS(Orders!G$5:G$24,Orders!C$5:C$24,A57) -> 0 | C57: =SUMIFS(Orders!I$5:I$24,Orders!C$5:C$24,A57) -> 0
A58: Feb-27 | B58: =SUMIFS(Orders!G$5:G$24,Orders!C$5:C$24,A58) -> 0 | C58: =SUMIFS(Orders!I$5:I$24,Orders!C$5:C$24,A58) -> 0
A59: Mar-27 | B59: =SUMIFS(Orders!G$5:G$24,Orders!C$5:C$24,A59) -> 0 | C59: =SUMIFS(Orders!I$5:I$24,Orders!C$5:C$24,A59) -> 0
A62: Price Desk Status | B62: Count
A63: Approved | B63: =COUNTIF('Price Desk'!L$5:L$24,"Approved") -> 8
A64: Pending | B64: =COUNTIF('Price Desk'!L$5:L$24,"Pending") -> 2
A65: Rejected | B65: =COUNTIF('Price Desk'!L$5:L$24,"Rejected") -> 0
A66: On Hold | B66: =COUNTIF('Price Desk'!L$5:L$24,"On Hold") -> 0

Sheet Targets & Settings
A1: AICERA SALES OPS — TARGETS & SETTINGS (Admin / Sales Head Only)
A2: Admin enters Top Line (Revenue) Targets in BLUE cells. Bottom Line = 8% of Top Line (auto). All other sheets read from here.
A4: GLOBAL SETTINGS
A5: Financial Year | B5: FY 2026-27
A6: Bottom Line % of Top Line | B6: 0.08 | C6: Change here → Bottom Line targets update everywhere
A7: Incentive % of Margin Earned | B7: 0.05 | C7: Incentive = 5% × Gross Margin earned from booked orders
A8: Price Desk Floor Margin % | B8: 0.06 | C8: Quotes below this margin need Price Desk approval
A10: Sales Person | B10: Top Line Target — Revenue (₹) | C10: Bottom Line Target — Margin (₹) | D10: Bottom Line % | E10: Incentive Potential @ 5% of Target (₹) | F10: Region / Segment | G10: Active? | H10: Notes
A11: Bhuvara PR | B11: 30000000 | C11: =B11*$B$6 -> 2400000 | D11: =IF(B11=0,0,C11/B11) -> 0.08 | E11: =C11*$B$7 -> 120000 | F11: Corporate — South | G11: Y
A12: Rahul Raju | B12: 25000000 | C12: =B12*$B$6 -> 2000000 | D12: =IF(B12=0,0,C12/B12) -> 0.08 | E12: =C12*$B$7 -> 100000 | F12: Corporate — West | G12: Y
A13: Laxman Kamath | B13: 45000000 | C13: =B13*$B$6 -> 3600000 | D13: =IF(B13=0,0,C13/B13) -> 0.08 | E13: =C13*$B$7 -> 180000 | F13: Strategic / Direct | G13: Y
A14: COMPANY TOTAL | B14: =SUM(B11:B13) -> 100000000 | C14: =SUM(C11:C13) -> 8000000 | D14: =IF(B14=0,0,C14/B14) -> 0.08 | E14: =SUM(E11:E13) -> 400000

Sheet Price Desk
A1: PRICE DESK — QUOTE APPROVAL REGISTER
A2: Sales team logs every quote BEFORE sending to customer. Quotes below floor margin (6%) are flagged and need Sales Head approval.
A4: Quote ID | B4: Date | C4: Sales Person | D4: Customer | E4: OEM / Product | F4: Quote Value (₹) | G4: Est. Cost (₹) | H4: Gross Margin (₹) | I4: Margin % | J4: Below Floor? | K4: Approval Needed | L4: Approval Status | M4: Approved By | N4: Approval Date | O4: Remarks
A5: QT-2601 | B5: 46118 | C5: Bhuvara PR | D5: Altimetrik | E5: Dell PowerEdge R760 x4 | F5: 4200000 | G5: 3860000 | H5: =F5-G5 -> 340000 | I5: =IF(F5=0,0,H5/F5) -> 0.080952381 | J5: =IF(I5<'Targets & Settings'!$B$8,"YES","NO") -> NO | K5: =IF(J5="YES","Sales Head","Auto (Above Floor)") -> Auto (Above Floor) | L5: Approved | M5: Laxman Kamath | N5: 46119 | O5: Strategic account — approved at 8.1%
A6: QT-2602 | B6: 46127 | C6: Rahul Raju | D6: Hikal Ltd | E6: Dell Latitude 5550 x60 | F6: 5400000 | G6: 5130000 | H6: =F6-G6 -> 270000 | I6: =IF(F6=0,0,H6/F6) -> 0.05 | J6: =IF(I6<'Targets & Settings'!$B$8,"YES","NO") -> YES | K6: =IF(J6="YES","Sales Head","Auto (Above Floor)") -> Sales Head | L6: Approved | M6: Laxman Kamath | N6: 46127 | O6: Volume deal, 5% OK vs competition
A7: QT-2603 | B7: 46146 | C7: Bhuvara PR | D7: CareSoft | E7: VMware VCF Renewal | F7: 8800000 | G7: 7920000 | H7: =F7-G7 -> 880000 | I7: =IF(F7=0,0,H7/F7) -> 0.1 | J7: =IF(I7<'Targets & Settings'!$B$8,"YES","NO") -> NO | K7: =IF(J7="YES","Sales Head","Auto (Above Floor)") -> Auto (Above Floor) | L7: Approved | M7: Laxman Kamath | N7: 46147 | O7: APJ pricing window
A8: QT-2604 | B8: 46162 | C8: Rahul Raju | D8: Omega Healthcare | E8: Dell PowerStore 500T | F8: 9500000 | G8: 8930000 | H8: =F8-G8 -> 570000 | I8: =IF(F8=0,0,H8/F8) -> 0.06 | J8: =IF(I8<'Targets & Settings'!$B$8,"YES","NO") -> NO | K8: =IF(J8="YES","Sales Head","Auto (Above Floor)") -> Auto (Above Floor) | L8: Approved | M8: Laxman Kamath | N8: 46163 | O8: Stock & Sell model
A9: QT-2605 | B9: 46176 | C9: Laxman Kamath | D9: ARIS Global | E9: DC Refresh — Servers + Storage | F9: 21500000 | G9: 19565000 | H9: =F9-G9 -> 1935000 | I9: =IF(F9=0,0,H9/F9) -> 0.09 | J9: =IF(I9<'Targets & Settings'!$B$8,"YES","NO") -> NO | K9: =IF(J9="YES","Sales Head","Auto (Above Floor)") -> Auto (Above Floor) | L9: Approved | M9: Laxman Kamath | N9: 46177 | O9: Lease model attached
A10: QT-2606 | B10: 46191 | C10: Bhuvara PR | D10: EIMS | E10: PowerEdge + Rack Infra | F10: 6200000 | G10: 5890000 | H10: =F10-G10 -> 310000 | I10: =IF(F10=0,0,H10/F10) -> 0.05 | J10: =IF(I10<'Targets & Settings'!$B$8,"YES","NO") -> YES | K10: =IF(J10="YES","Sales Head","Auto (Above Floor)") -> Sales Head | L10: Approved | M10: Laxman Kamath | N10: 46192 | O10: Power sizing done
A11: QT-2607 | B11: 46198 | C11: Rahul Raju | D11: Twilight Systems | E11: Dell OptiPlex x40 + Monitors | F11: 3100000 | G11: 2976000 | H11: =F11-G11 -> 124000 | I11: =IF(F11=0,0,H11/F11) -> 0.04 | J11: =IF(I11<'Targets & Settings'!$B$8,"YES","NO") -> YES | K11: =IF(J11="YES","Sales Head","Auto (Above Floor)") -> Sales Head | L11: Pending | O11: Awaiting distributor best cost
A12: QT-2608 | B12: 46205 | C12: Bhuvara PR | D12: Kanva Fashions | E12: PowerVault ME5 + Switches | F12: 4800000 | G12: 4416000 | H12: =F12-G12 -> 384000 | I12: =IF(F12=0,0,H12/F12) -> 0.08 | J12: =IF(I12<'Targets & Settings'!$B$8,"YES","NO") -> NO | K12: =IF(J12="YES","Sales Head","Auto (Above Floor)") -> Auto (Above Floor) | L12: Approved | M12: Laxman Kamath | N12: 46206
A13: QT-2609 | B13: 46209 | C13: Laxman Kamath | D13: NextGen Pharma | E13: HCI — VxRail 4 Node | F13: 14500000 | G13: 13775000 | H13: =F13-G13 -> 725000 | I13: =IF(F13=0,0,H13/F13) -> 0.05 | J13: =IF(I13<'Targets & Settings'!$B$8,"YES","NO") -> YES | K13: =IF(J13="YES","Sales Head","Auto (Above Floor)") -> Sales Head | L13: Pending | O13: Competing with HPE — need floor waiver
A14: QT-2610 | B14: 46210 | C14: Rahul Raju | D14: Altimetrik | E14: Docking + Peripherals | F14: 900000 | G14: 855000 | H14: =F14-G14 -> 45000 | I14: =IF(F14=0,0,H14/F14) -> 0.05 | J14: =IF(I14<'Targets & Settings'!$B$8,"YES","NO") -> YES | K14: =IF(J14="YES","Sales Head","Auto (Above Floor)") -> Sales Head | L14: Approved | M14: Rahul Raju | N14: 46210 | O14: Above floor — self-approved
H15: =IF(F15="","",F15-G15) | I15: =IF(OR(F15="",F15=0),"",H15/F15) | J15: =IF(F15="","",IF(I15<'Targets & Settings'!$B$8,"YES","NO")) | K15: =IF(F15="","",IF(J15="YES","Sales Head","Auto (Above Floor)"))
H16: =IF(F16="","",F16-G16) | I16: =IF(OR(F16="",F16=0),"",H16/F16) | J16: =IF(F16="","",IF(I16<'Targets & Settings'!$B$8,"YES","NO")) | K16: =IF(F16="","",IF(J16="YES","Sales Head","Auto (Above Floor)"))
H17: =IF(F17="","",F17-G17) | I17: =IF(OR(F17="",F17=0),"",H17/F17) | J17: =IF(F17="","",IF(I17<'Targets & Settings'!$B$8,"YES","NO")) | K17: =IF(F17="","",IF(J17="YES","Sales Head","Auto (Above Floor)"))
H18: =IF(F18="","",F18-G18) | I18: =IF(OR(F18="",F18=0),"",H18/F18) | J18: =IF(F18="","",IF(I18<'Targets & Settings'!$B$8,"YES","NO")) | K18: =IF(F18="","",IF(J18="YES","Sales Head","Auto (Above Floor)"))
H19: =IF(F19="","",F19-G19) | I19: =IF(OR(F19="",F19=0),"",H19/F19) | J19: =IF(F19="","",IF(I19<'Targets & Settings'!$B$8,"YES","NO")) | K19: =IF(F19="","",IF(J19="YES","Sales Head","Auto (Above Floor)"))
H20: =IF(F20="","",F20-G20) | I20: =IF(OR(F20="",F20=0),"",H20/F20) | J20: =IF(F20="","",IF(I20<'Targets & Settings'!$B$8,"YES","NO")) | K20: =IF(F20="","",IF(J20="YES","Sales Head","Auto (Above Floor)"))
H21: =IF(F21="","",F21-G21) | I21: =IF(OR(F21="",F21=0),"",H21/F21) | J21: =IF(F21="","",IF(I21<'Targets & Settings'!$B$8,"YES","NO")) | K21: =IF(F21="","",IF(J21="YES","Sales Head","Auto (Above Floor)"))
H22: =IF(F22="","",F22-G22) | I22: =IF(OR(F22="",F22=0),"",H22/F22) | J22: =IF(F22="","",IF(I22<'Targets & Settings'!$B$8,"YES","NO")) | K22: =IF(F22="","",IF(J22="YES","Sales Head","Auto (Above Floor)"))
H23: =IF(F23="","",F23-G23) | I23: =IF(OR(F23="",F23=0),"",H23/F23) | J23: =IF(F23="","",IF(I23<'Targets & Settings'!$B$8,"YES","NO")) | K23: =IF(F23="","",IF(J23="YES","Sales Head","Auto (Above Floor)"))
H24: =IF(F24="","",F24-G24) | I24: =IF(OR(F24="",F24=0),"",H24/F24) | J24: =IF(F24="","",IF(I24<'Targets & Settings'!$B$8,"YES","NO")) | K24: =IF(F24="","",IF(J24="YES","Sales Head","Auto (Above Floor)"))

Sheet Order Checklist
A1: ORDER EXECUTION CHECKLIST
A2: Mark each gate Y/N per order. % Complete auto-calculates. An order is 'Closed' only at 100%.
A4: Order ID | B4: Customer | C4: Sales Person | D4: Ops Owner | E4: Customer PO Received | F4: PO Value & Terms Verified | G4: OEM Quote Validity Checked | H4: Distributor PO Placed | I4: OEM Order Acknowledged | J4: Delivery / GRN Done | K4: Installation Complete | L4: Invoice Raised | M4: Payment Terms Confirmed | N4: Payment Collected | O4: % Complete | P4: Stage
A5: ORD-2601 | B5: Altimetrik | C5: Bhuvara PR | D5: Chetan | E5: Y | F5: Y | G5: Y | H5: Y | I5: Y | J5: Y | K5: Y | L5: Y | M5: Y | N5: Y | O5: =COUNTIF(E5:N5,"Y")/10 -> 1 | P5: =IF(O5=1,"CLOSED",IF(O5>=0.7,"ADVANCED",IF(O5>=0.4,"IN PROGRESS","EARLY"))) -> CLOSED
A6: ORD-2602 | B6: Hikal Ltd | C6: Rahul Raju | D6: Bhoomika | E6: Y | F6: Y | G6: Y | H6: Y | I6: Y | J6: Y | K6: Y | L6: Y | M6: Y | N6: Y | O6: =COUNTIF(E6:N6,"Y")/10 -> 1 | P6: =IF(O6=1,"CLOSED",IF(O6>=0.7,"ADVANCED",IF(O6>=0.4,"IN PROGRESS","EARLY"))) -> CLOSED
A7: ORD-2603 | B7: CareSoft | C7: Bhuvara PR | D7: Chetan | E7: Y | F7: Y | G7: Y | H7: Y | I7: Y | J7: Y | K7: Y | L7: Y | M7: Y | N7: N | O7: =COUNTIF(E7:N7,"Y")/10 -> 0.9 | P7: =IF(O7=1,"CLOSED",IF(O7>=0.7,"ADVANCED",IF(O7>=0.4,"IN PROGRESS","EARLY"))) -> ADVANCED
A8: ORD-2604 | B8: Omega Healthcare | C8: Rahul Raju | D8: Deekshit | E8: Y | F8: Y | G8: Y | H8: Y | I8: Y | J8: N | K8: N | L8: N | M8: Y | N8: N | O8: =COUNTIF(E8:N8,"Y")/10 -> 0.6 | P8: =IF(O8=1,"CLOSED",IF(O8>=0.7,"ADVANCED",IF(O8>=0.4,"IN PROGRESS","EARLY"))) -> IN PROGRESS
A9: ORD-2605 | B9: ARIS Global | C9: Laxman Kamath | D9: Chetan | E9: Y | F9: Y | G9: Y | H9: Y | I9: N | J9: N | K9: N | L9: N | M9: Y | N9: N | O9: =COUNTIF(E9:N9,"Y")/10 -> 0.5 | P9: =IF(O9=1,"CLOSED",IF(O9>=0.7,"ADVANCED",IF(O9>=0.4,"IN PROGRESS","EARLY"))) -> IN PROGRESS
A10: ORD-2606 | B10: EIMS | C10: Bhuvara PR | D10: Bhoomika | E10: Y | F10: Y | G10: Y | H10: Y | I10: Y | J10: Y | K10: N | L10: Y | M10: Y | N10: N | O10: =COUNTIF(E10:N10,"Y")/10 -> 0.8 | P10: =IF(O10=1,"CLOSED",IF(O10>=0.7,"ADVANCED",IF(O10>=0.4,"IN PROGRESS","EARLY"))) -> ADVANCED
A11: ORD-2607 | B11: Kanva Fashions | C11: Bhuvara PR | D11: Deekshit | E11: Y | F11: Y | G11: Y | H11: N | I11: N | J11: N | K11: N | L11: N | M11: Y | N11: N | O11: =COUNTIF(E11:N11,"Y")/10 -> 0.4 | P11: =IF(O11=1,"CLOSED",IF(O11>=0.7,"ADVANCED",IF(O11>=0.4,"IN PROGRESS","EARLY"))) -> IN PROGRESS
A12: ORD-2608 | B12: Altimetrik | C12: Rahul Raju | D12: Chetan | E12: Y | F12: Y | G12: N | H12: N | I12: N | J12: N | K12: N | L12: N | M12: N | N12: N | O12: =COUNTIF(E12:N12,"Y")/10 -> 0.2 | P12: =IF(O12=1,"CLOSED",IF(O12>=0.7,"ADVANCED",IF(O12>=0.4,"IN PROGRESS","EARLY"))) -> EARLY
O13: =IF(A13="","",COUNTIF(E13:N13,"Y")/10) | P13: =IF(A13="","",IF(O13=1,"CLOSED",IF(O13>=0.7,"ADVANCED",IF(O13>=0.4,"IN PROGRESS","EARLY"))))
O14: =IF(A14="","",COUNTIF(E14:N14,"Y")/10) | P14: =IF(A14="","",IF(O14=1,"CLOSED",IF(O14>=0.7,"ADVANCED",IF(O14>=0.4,"IN PROGRESS","EARLY"))))
O15: =IF(A15="","",COUNTIF(E15:N15,"Y")/10) | P15: =IF(A15="","",IF(O15=1,"CLOSED",IF(O15>=0.7,"ADVANCED",IF(O15>=0.4,"IN PROGRESS","EARLY"))))
O16: =IF(A16="","",COUNTIF(E16:N16,"Y")/10) | P16: =IF(A16="","",IF(O16=1,"CLOSED",IF(O16>=0.7,"ADVANCED",IF(O16>=0.4,"IN PROGRESS","EARLY"))))
O17: =IF(A17="","",COUNTIF(E17:N17,"Y")/10) | P17: =IF(A17="","",IF(O17=1,"CLOSED",IF(O17>=0.7,"ADVANCED",IF(O17>=0.4,"IN PROGRESS","EARLY"))))
O18: =IF(A18="","",COUNTIF(E18:N18,"Y")/10) | P18: =IF(A18="","",IF(O18=1,"CLOSED",IF(O18>=0.7,"ADVANCED",IF(O18>=0.4,"IN PROGRESS","EARLY"))))
O19: =IF(A19="","",COUNTIF(E19:N19,"Y")/10) | P19: =IF(A19="","",IF(O19=1,"CLOSED",IF(O19>=0.7,"ADVANCED",IF(O19>=0.4,"IN PROGRESS","EARLY"))))
O20: =IF(A20="","",COUNTIF(E20:N20,"Y")/10) | P20: =IF(A20="","",IF(O20=1,"CLOSED",IF(O20>=0.7,"ADVANCED",IF(O20>=0.4,"IN PROGRESS","EARLY"))))
O21: =IF(A21="","",COUNTIF(E21:N21,"Y")/10) | P21: =IF(A21="","",IF(O21=1,"CLOSED",IF(O21>=0.7,"ADVANCED",IF(O21>=0.4,"IN PROGRESS","EARLY"))))
O22: =IF(A22="","",COUNTIF(E22:N22,"Y")/10) | P22: =IF(A22="","",IF(O22=1,"CLOSED",IF(O22>=0.7,"ADVANCED",IF(O22>=0.4,"IN PROGRESS","EARLY"))))

Sheet Orders
A1: ORDER REGISTER — BOOKED ORDERS
A2: Every booked order is logged here. Gross Margin auto-calculates and rolls up to the Incentive sheet & Dashboard (Margin Quota).
A4: Order ID | B4: PO Date | C4: Month | D4: Sales Person | E4: Customer | F4: Linked Quote | G4: Order Value — Revenue (₹) | H4: Cost (₹) | I4: Gross Margin (₹) | J4: Margin % | K4: Order Status | L4: Payment Status
A5: ORD-2601 | B5: 46122 | C5: =IF(B5="","",TEXT(B5,"MMM-YY")) -> Apr-26 | D5: Bhuvara PR | E5: Altimetrik | F5: QT-2601 | G5: 42000000 | H5: 38600000 | I5: =G5-H5 -> 3400000 | J5: =IF(G5=0,0,I5/G5) -> 0.080952381 | K5: Delivered | L5: Received
A6: ORD-2602 | B6: 46134 | C6: =IF(B6="","",TEXT(B6,"MMM-YY")) -> Apr-26 | D6: Rahul Raju | E6: Hikal Ltd | F6: QT-2602 | G6: 54000000 | H6: 51300000 | I6: =G6-H6 -> 2700000 | J6: =IF(G6=0,0,I6/G6) -> 0.05 | K6: Delivered | L6: Received
A7: ORD-2603 | B7: 46154 | C7: =IF(B7="","",TEXT(B7,"MMM-YY")) -> May-26 | D7: Bhuvara PR | E7: CareSoft | F7: QT-2603 | G7: 8800000 | H7: 7920000 | I7: =G7-H7 -> 880000 | J7: =IF(G7=0,0,I7/G7) -> 0.1 | K7: Delivered | L7: Part Received
A8: ORD-2604 | B8: 46170 | C8: =IF(B8="","",TEXT(B8,"MMM-YY")) -> May-26 | D8: Rahul Raju | E8: Omega Healthcare | F8: QT-2604 | G8: 9500000 | H8: 8930000 | I8: =G8-H8 -> 570000 | J8: =IF(G8=0,0,I8/G8) -> 0.06 | K8: In Transit | L8: Pending
A9: ORD-2605 | B9: 46183 | C9: =IF(B9="","",TEXT(B9,"MMM-YY")) -> Jun-26 | D9: Laxman Kamath | E9: ARIS Global | F9: QT-2605 | G9: 21500000 | H9: 19565000 | I9: =G9-H9 -> 1935000 | J9: =IF(G9=0,0,I9/G9) -> 0.09 | K9: Processing | L9: Advance Received
A10: ORD-2606 | B10: 46197 | C10: =IF(B10="","",TEXT(B10,"MMM-YY")) -> Jun-26 | D10: Bhuvara PR | E10: EIMS | F10: QT-2606 | G10: 6200000 | H10: 5890000 | I10: =G10-H10 -> 310000 | J10: =IF(G10=0,0,I10/G10) -> 0.05 | K10: Delivered | L10: Pending
A11: ORD-2607 | B11: 46208 | C11: =IF(B11="","",TEXT(B11,"MMM-YY")) -> Jul-26 | D11: Bhuvara PR | E11: Kanva Fashions | F11: QT-2608 | G11: 4800000 | H11: 4416000 | I11: =G11-H11 -> 384000 | J11: =IF(G11=0,0,I11/G11) -> 0.08 | K11: Processing | L11: Pending
A12: ORD-2608 | B12: 46210 | C12: =IF(B12="","",TEXT(B12,"MMM-YY")) -> Jul-26 | D12: Rahul Raju | E12: Altimetrik | F12: QT-2610 | G12: 900000 | H12: 855000 | I12: =G12-H12 -> 45000 | J12: =IF(G12=0,0,I12/G12) -> 0.05 | K12: Processing | L12: Pending
C13: =IF(B13="","",TEXT(B13,"MMM-YY")) | I13: =IF(G13="","",G13-H13) | J13: =IF(OR(G13="",G13=0),"",I13/G13)
C14: =IF(B14="","",TEXT(B14,"MMM-YY")) | I14: =IF(G14="","",G14-H14) | J14: =IF(OR(G14="",G14=0),"",I14/G14)
C15: =IF(B15="","",TEXT(B15,"MMM-YY")) | I15: =IF(G15="","",G15-H15) | J15: =IF(OR(G15="",G15=0),"",I15/G15)
C16: =IF(B16="","",TEXT(B16,"MMM-YY")) | I16: =IF(G16="","",G16-H16) | J16: =IF(OR(G16="",G16=0),"",I16/G16)
C17: =IF(B17="","",TEXT(B17,"MMM-YY")) | I17: =IF(G17="","",G17-H17) | J17: =IF(OR(G17="",G17=0),"",I17/G17)
C18: =IF(B18="","",TEXT(B18,"MMM-YY")) | I18: =IF(G18="","",G18-H18) | J18: =IF(OR(G18="",G18=0),"",I18/G18)
C19: =IF(B19="","",TEXT(B19,"MMM-YY")) | I19: =IF(G19="","",G19-H19) | J19: =IF(OR(G19="",G19=0),"",I19/G19)
C20: =IF(B20="","",TEXT(B20,"MMM-YY")) | I20: =IF(G20="","",G20-H20) | J20: =IF(OR(G20="",G20=0),"",I20/G20)
C21: =IF(B21="","",TEXT(B21,"MMM-YY")) | I21: =IF(G21="","",G21-H21) | J21: =IF(OR(G21="",G21=0),"",I21/G21)
C22: =IF(B22="","",TEXT(B22,"MMM-YY")) | I22: =IF(G22="","",G22-H22) | J22: =IF(OR(G22="",G22=0),"",I22/G22)
C23: =IF(B23="","",TEXT(B23,"MMM-YY")) | I23: =IF(G23="","",G23-H23) | J23: =IF(OR(G23="",G23=0),"",I23/G23)
C24: =IF(B24="","",TEXT(B24,"MMM-YY")) | I24: =IF(G24="","",G24-H24) | J24: =IF(OR(G24="",G24=0),"",I24/G24)
E25: TOTAL BOOKED | G25: =SUM(G5:G24) -> 147700000 | H25: =SUM(H5:H24) -> 137476000 | I25: =SUM(I5:I24) -> 10224000 | J25: =IF(G25=0,0,I25/G25) -> 0.069221395

Sheet Incentive
A1: INCENTIVE ENGINE — REVENUE / MARGIN TO GO & PAYOUT
A2: Auto-calculated. Margin Quota = SUM of Gross Margin from booked orders. Incentive = 5% × Margin Earned. To-Go = Target − Achieved.
A4: Sales Person | B4: Top Line Target (₹) | C4: Revenue Booked (₹) | D4: Revenue To Go (₹) | E4: Revenue Achieved % | F4: Bottom Line Target (₹) | G4: Margin Earned (₹) | H4: Margin To Go (₹) | I4: Margin Achieved % | J4: Incentive Payable @5% (₹)
A5: Bhuvara PR | B5: ='Targets & Settings'!B11 -> 30000000 | C5: =SUMIFS(Orders!G$5:G$24,Orders!D$5:D$24,A5) -> 61800000 | D5: =MAX(B5-C5,0) -> 0 | E5: =IF(B5=0,0,C5/B5) -> 2.06 | F5: ='Targets & Settings'!C11 -> 2400000 | G5: =SUMIFS(Orders!I$5:I$24,Orders!D$5:D$24,A5) -> 4974000 | H5: =MAX(F5-G5,0) -> 0 | I5: =IF(F5=0,0,G5/F5) -> 2.0725 | J5: =G5*'Targets & Settings'!$B$7 -> 248700
A6: Rahul Raju | B6: ='Targets & Settings'!B12 -> 25000000 | C6: =SUMIFS(Orders!G$5:G$24,Orders!D$5:D$24,A6) -> 64400000 | D6: =MAX(B6-C6,0) -> 0 | E6: =IF(B6=0,0,C6/B6) -> 2.576 | F6: ='Targets & Settings'!C12 -> 2000000 | G6: =SUMIFS(Orders!I$5:I$24,Orders!D$5:D$24,A6) -> 3315000 | H6: =MAX(F6-G6,0) -> 0 | I6: =IF(F6=0,0,G6/F6) -> 1.6575 | J6: =G6*'Targets & Settings'!$B$7 -> 165750
A7: Laxman Kamath | B7: ='Targets & Settings'!B13 -> 45000000 | C7: =SUMIFS(Orders!G$5:G$24,Orders!D$5:D$24,A7) -> 21500000 | D7: =MAX(B7-C7,0) -> 23500000 | E7: =IF(B7=0,0,C7/B7) -> 0.47777778 | F7: ='Targets & Settings'!C13 -> 3600000 | G7: =SUMIFS(Orders!I$5:I$24,Orders!D$5:D$24,A7) -> 1935000 | H7: =MAX(F7-G7,0) -> 1665000 | I7: =IF(F7=0,0,G7/F7) -> 0.5375 | J7: =G7*'Targets & Settings'!$B$7 -> 96750
A8: COMPANY TOTAL | B8: =SUM(B5:B7) -> 100000000 | C8: =SUM(C5:C7) -> 147700000 | D8: =SUM(D5:D7) -> 23500000 | E8: =IF(B8=0,0,C8/B8) -> 1.477 | F8: =SUM(F5:F7) -> 8000000 | G8: =SUM(G5:G7) -> 10224000 | H8: =SUM(H5:H7) -> 1665000 | I8: =IF(F8=0,0,G8/F8) -> 1.278 | J8: =SUM(J5:J7) -> 511200
A10: Rule: Incentive = 5% × Gross Margin actually earned (sum of booked orders). Full-year incentive potential = 5% × Bottom Line Target if 100% achieved.

Sheet Dev Spec (Web App)
A1: DEVELOPER SPECIFICATION — AICERA SALES OPS WEB APP
A2: Hand this sheet to the dev team. Modules, fields, business rules and roles below mirror the working sheets in this workbook.
A4: SECTION | B4: ITEM | C4: DETAILS
A5: 1. Modules | B5: M1 — Price Desk | C5: Quote approval workflow. Sales raises quote → system checks Margin % vs Floor (6%, configurable) → below floor routes to Sales Head for Approve/Reject/Hold → audit trail (who, when, remarks).
B6: M2 — Order Register | C6: Booked orders with Revenue, Cost, auto Gross Margin. Links back to approved Quote ID. Status: Processing/In Transit/Delivered/Installed/Cancelled + Payment status.
B7: M3 — Order Checklist | C7: 10 execution gates per order (see Order Checklist sheet columns E–N). % complete auto. Order 'Closed' only at 100%. Ops owner assignable (Chetan/Bhoomika/Deekshit).
B8: M4 — Targets (Admin) | C8: Sales Head/Admin sets Top Line (Revenue) target per salesperson per FY. Bottom Line auto = Top Line × 8% (configurable global setting).
B9: M5 — Incentive Engine | C9: Auto-computed. No manual entry.
B10: M6 — Dashboard | C10: KPI cards + 4 charts as on the Dashboard sheet. Filters: FY, salesperson, month.
A11: 2. Business Rules | B11: R1 — Bottom Line | C11: Bottom Line Target = Top Line Target × 8%. The 8% lives in Settings ('Targets & Settings'!B6) and must be editable by Admin only.
B12: R2 — Margin Quota | C12: Margin Quota (earned) = SUM(Gross Margin) of all booked orders for that salesperson. Gross Margin = Order Value − Cost.
B13: R3 — Revenue To Go | C13: Revenue To Go = Top Line Target − SUM(Order Value). Floor at 0 (never negative).
B14: R4 — Margin To Go | C14: Margin To Go = Bottom Line Target − Margin Quota earned. Floor at 0.
B15: R5 — Incentive | C15: Incentive Payable = 5% × Gross Margin earned (accrues per order; settle half-yearly or annually as per HR policy). 5% is configurable ('Targets & Settings'!B7). At 100% achievement, payout = 5% × Bottom Line Target.
B16: R6 — Price Desk Gate | C16: If Quote Margin % < Floor Margin % → status forced to 'Pending', Sales Head approval mandatory before quote is released to customer. Above floor → auto-approved, still logged.
B17: R7 — Quote→Order Link | C17: An order should reference an Approved quote ID. Block order creation against Rejected quotes.
A18: 3. Roles | B18: Admin / Sales Head | C18: Full access. Sets targets, floor %, incentive %. Approves/rejects Price Desk requests. Sees all dashboards.
B19: Sales Person | C19: Raises quotes, logs orders, views OWN dashboard: targets, to-go, incentive. Cannot edit targets or approve own below-floor quotes.
B20: Ops (Procurement) | C20: Updates Order Checklist gates, order status, payment status. Read-only on incentive.
A21: 4. Data Model (key fields) | B21: Quote | C21: quote_id, date, salesperson_id, customer, oem_product, quote_value, est_cost, margin_amt*, margin_pct*, below_floor*, approval_status, approved_by, approval_date, remarks (* = computed)
B22: Order | C22: order_id, po_date, month*, salesperson_id, customer, quote_id (FK), order_value, cost, gross_margin*, margin_pct*, order_status, payment_status
B23: Checklist | C23: order_id (FK), 10 boolean gates, pct_complete*, stage*, ops_owner
B24: Target | C24: fy, salesperson_id, topline_target, bottomline_target* (=8%), incentive_potential*
A25: 5. Nice-to-haves | C25: Email/WhatsApp alert to Sales Head on new below-floor quote; SLA timer on pending approvals; monthly auto-report PDF; export to Excel matching this workbook's layout.
